qaldron/__init__.py
qaldron/api/__init__.py
qaldron/api/api_keys.py
qaldron/api/main.py
qaldron/api/models.py
qaldron/api/registry.py
qaldron/api/routes/__init__.py
qaldron/api/routes/agents.py
qaldron/api/routes/messages.py
qaldron/config/__init__.py
qaldron/config/config.yaml
qaldron/layer1/__init__.py
qaldron/layer1/mark_blu.py
qaldron/layer1/quantum_sim.py
qaldron/layer2/__init__.py
qaldron/layer2/crypto.py
qaldron/layer2/entropy.py
qaldron/layer2/message_envelope.py
qaldron/layer2/secure_messenger.py
qaldron/sdk/__init__.py
qaldron/sdk/agent_client.py
qaldron/sdk/message_queue.py
qaldron-1.0.0.dist-info/METADATA
qaldron-1.0.0.dist-info/WHEEL
qaldron-1.0.0.dist-info/entry_points.txt
qaldron-1.0.0.dist-info/top_level.txt
qaldron-1.0.0.dist-info/RECORD
